[
  {
    "LiveFrom": "16/03/2020",
    "CaseTypeID": "FinancialRemedyMVP2",
    "CaseFieldID": "ApplicantOrganisationPolicy",
    "UserRole": "caseworker-caa",
    "CRUD": "CRU"
  },
  {
    "LiveFrom": "16/03/2020",
    "CaseTypeID": "FinancialRemedyMVP2",
    "CaseFieldID": "RespondentOrganisationPolicy",
    "UserRole": "caseworker-caa",
    "CRUD": "CRU"
  },
  {
    "LiveFrom": "16/03/2020",
    "CaseTypeID": "FinancialRemedyMVP2",
    "CaseFieldID": "divorceCaseNumber",
    "UserRole": "caseworker-caa",
    "CRUD": "CRU"
  },
  {
    "LiveFrom": "16/03/2020",
    "CaseTypeID": "FinancialRemedyMVP2",
    "CaseFieldID": "applicantLName",
    "UserRole": "caseworker-caa",
    "CRUD": "CRU"
  },
  {
    "LiveFrom": "16/03/2020",
    "CaseTypeID": "FinancialRemedyMVP2",
    "CaseFieldID": "appRespondentLName",
    "UserRole": "caseworker-caa",
    "CRUD": "CRU"
  },
  {
    "LiveFrom": "16/03/2020",
    "CaseTypeID": "FinancialRemedyMVP2",
    "CaseFieldID": "dueDate",
    "UserRole": "caseworker-caa",
    "CRUD": "CRU"
  },
  {
    "LiveFrom": "16/03/2020",
    "CaseTypeID": "FinancialRemedyMVP2",
    "CaseFieldID": "issueDate",
    "UserRole": "caseworker-caa",
    "CRUD": "CRU"
  },
  {
    "LiveFrom": "01/10/2020",
    "CaseTypeID": "FinancialRemedyMVP2",
    "CaseFieldID": "applicantRepresented",
    "UserRole": "caseworker-caa",
    "CRUD": "CRU"
  },
  {
    "LiveFrom": "01/10/2020",
    "CaseTypeID": "FinancialRemedyMVP2",
    "CaseFieldID": "applicantAddress",
    "UserRole": "caseworker-caa",
    "CRUD": "CRU"
  },
  {
    "LiveFrom": "01/10/2020",
    "CaseTypeID": "FinancialRemedyMVP2",
    "CaseFieldID": "applicantPhone",
    "UserRole": "caseworker-caa",
    "CRUD": "CRU"
  },
  {
    "LiveFrom": "01/10/2020",
    "CaseTypeID": "FinancialRemedyMVP2",
    "CaseFieldID": "applicantEmail",
    "UserRole": "caseworker-caa",
    "CRUD": "CRU"
  },
  {
    "LiveFrom": "01/10/2020",
    "CaseTypeID": "FinancialRemedyMVP2",
    "CaseFieldID": "solicitorName",
    "UserRole": "caseworker-caa",
    "CRUD": "CRU"
  },
  {
    "LiveFrom": "01/10/2020",
    "CaseTypeID": "FinancialRemedyMVP2",
    "CaseFieldID": "solicitorFirm",
    "UserRole": "caseworker-caa",
    "CRUD": "CRU"
  },
  {
    "LiveFrom": "01/10/2020",
    "CaseTypeID": "FinancialRemedyMVP2",
    "CaseFieldID": "solicitorReference",
    "UserRole": "caseworker-caa",
    "CRUD": "CRU"
  },
  {
    "LiveFrom": "01/10/2020",
    "CaseTypeID": "FinancialRemedyMVP2",
    "CaseFieldID": "solicitorAddress",
    "UserRole": "caseworker-caa",
    "CRUD": "CRU"
  },
  {
    "LiveFrom": "01/10/2020",
    "CaseTypeID": "FinancialRemedyMVP2",
    "CaseFieldID": "solicitorPhone",
    "UserRole": "caseworker-caa",
    "CRUD": "CRU"
  },
  {
    "LiveFrom": "01/10/2020",
    "CaseTypeID": "FinancialRemedyMVP2",
    "CaseFieldID": "solicitorEmail",
    "UserRole": "caseworker-caa",
    "CRUD": "CRU"
  },
  {
    "LiveFrom": "01/10/2020",
    "CaseTypeID": "FinancialRemedyMVP2",
    "CaseFieldID": "solicitorDXnumber",
    "UserRole": "caseworker-caa",
    "CRUD": "CRU"
  },
  {
    "LiveFrom": "01/10/2020",
    "CaseTypeID": "FinancialRemedyMVP2",
    "CaseFieldID": "solicitorAgreeToReceiveEmails",
    "UserRole": "caseworker-caa",
    "CRUD": "CRU"
  },
  {
    "LiveFrom": "01/10/2020",
    "CaseTypeID": "FinancialRemedyMVP2",
    "CaseFieldID": "divorceStageReached",
    "UserRole": "caseworker-caa",
    "CRUD": "CRU"
  },
  {
    "LiveFrom": "01/10/2020",
    "CaseTypeID": "FinancialRemedyMVP2",
    "CaseFieldID": "divorceUploadEvidence1",
    "UserRole": "caseworker-caa",
    "CRUD": "CRU"
  },
  {
    "LiveFrom": "01/10/2020",
    "CaseTypeID": "FinancialRemedyMVP2",
    "CaseFieldID": "divorceDecreeNisiDate",
    "UserRole": "caseworker-caa",
    "CRUD": "CRU"
  },
  {
    "LiveFrom": "01/10/2020",
    "CaseTypeID": "FinancialRemedyMVP2",
    "CaseFieldID": "divorceUploadEvidence2",
    "UserRole": "caseworker-caa",
    "CRUD": "CRU"
  },
  {
    "LiveFrom": "01/10/2020",
    "CaseTypeID": "FinancialRemedyMVP2",
    "CaseFieldID": "divorceDecreeAbsoluteDate",
    "UserRole": "caseworker-caa",
    "CRUD": "CRU"
  },
  {
    "LiveFrom": "01/10/2020",
    "CaseTypeID": "FinancialRemedyMVP2",
    "CaseFieldID": "applicantFMName",
    "UserRole": "caseworker-caa",
    "CRUD": "CRU"
  },
  {
    "LiveFrom": "01/10/2020",
    "CaseTypeID": "FinancialRemedyMVP2",
    "CaseFieldID": "regionList",
    "UserRole": "caseworker-caa",
    "CRUD": "CRU"
  },
  {
    "LiveFrom": "01/10/2020",
    "CaseTypeID": "FinancialRemedyMVP2",
    "CaseFieldID": "midlandsFRCList",
    "UserRole": "caseworker-caa",
    "CRUD": "CRU"
  },
  {
    "LiveFrom": "01/10/2020",
    "CaseTypeID": "FinancialRemedyMVP2",
    "CaseFieldID": "londonFRCList",
    "UserRole": "caseworker-caa",
    "CRUD": "CRU"
  },
  {
    "LiveFrom": "01/10/2020",
    "CaseTypeID": "FinancialRemedyMVP2",
    "CaseFieldID": "northWestFRCList",
    "UserRole": "caseworker-caa",
    "CRUD": "CRU"
  },
  {
    "LiveFrom": "01/10/2020",
    "CaseTypeID": "FinancialRemedyMVP2",
    "CaseFieldID": "northEastFRCList",
    "UserRole": "caseworker-caa",
    "CRUD": "CRU"
  },
  {
    "LiveFrom": "01/10/2020",
    "CaseTypeID": "FinancialRemedyMVP2",
    "CaseFieldID": "southEastFRCList",
    "UserRole": "caseworker-caa",
    "CRUD": "CRU"
  },
  {
    "LiveFrom": "01/10/2020",
    "CaseTypeID": "FinancialRemedyMVP2",
    "CaseFieldID": "southWestFRCList",
    "UserRole": "caseworker-caa",
    "CRUD": "CRU"
  },
  {
    "LiveFrom": "01/10/2020",
    "CaseTypeID": "FinancialRemedyMVP2",
    "CaseFieldID": "walesFRCList",
    "UserRole": "caseworker-caa",
    "CRUD": "CRU"
  },
  {
    "LiveFrom": "01/10/2020",
    "CaseTypeID": "FinancialRemedyMVP2",
    "CaseFieldID": "nottinghamCourtList",
    "UserRole": "caseworker-caa",
    "CRUD": "CRU"
  },
  {
    "LiveFrom": "01/10/2020",
    "CaseTypeID": "FinancialRemedyMVP2",
    "CaseFieldID": "birminghamCourtList",
    "UserRole": "caseworker-caa",
    "CRUD": "CRU"
  },
  {
    "LiveFrom": "01/10/2020",
    "CaseTypeID": "FinancialRemedyMVP2",
    "CaseFieldID": "londonCourtList",
    "UserRole": "caseworker-caa",
    "CRUD": "CRU"
  },
  {
    "LiveFrom": "01/10/2020",
    "CaseTypeID": "FinancialRemedyMVP2",
    "CaseFieldID": "liverpoolCourtList",
    "UserRole": "caseworker-caa",
    "CRUD": "CRU"
  },
  {
    "LiveFrom": "01/10/2020",
    "CaseTypeID": "FinancialRemedyMVP2",
    "CaseFieldID": "manchesterCourtList",
    "UserRole": "caseworker-caa",
    "CRUD": "CRU"
  },
  {
    "LiveFrom": "01/10/2020",
    "CaseTypeID": "FinancialRemedyMVP2",
    "CaseFieldID": "clevelandCourtList",
    "UserRole": "caseworker-caa",
    "CRUD": "CRU"
  },
  {
    "LiveFrom": "01/10/2020",
    "CaseTypeID": "FinancialRemedyMVP2",
    "CaseFieldID": "nwyorkshireCourtList",
    "UserRole": "caseworker-caa",
    "CRUD": "CRU"
  },
  {
    "LiveFrom": "01/10/2020",
    "CaseTypeID": "FinancialRemedyMVP2",
    "CaseFieldID": "humberCourtList",
    "UserRole": "caseworker-caa",
    "CRUD": "CRU"
  },
  {
    "LiveFrom": "01/10/2020",
    "CaseTypeID": "FinancialRemedyMVP2",
    "CaseFieldID": "kentSurreyCourtList",
    "UserRole": "caseworker-caa",
    "CRUD": "CRU"
  },
  {
    "LiveFrom": "01/10/2020",
    "CaseTypeID": "FinancialRemedyMVP2",
    "CaseFieldID": "newportCourtList",
    "UserRole": "caseworker-caa",
    "CRUD": "CRU"
  },
  {
    "LiveFrom": "01/10/2020",
    "CaseTypeID": "FinancialRemedyMVP2",
    "CaseFieldID": "swanseaCourtList",
    "UserRole": "caseworker-caa",
    "CRUD": "CRU"
  },
  {
    "LiveFrom": "01/10/2020",
    "CaseTypeID": "FinancialRemedyMVP2",
    "CaseFieldID": "appRespondentFMName",
    "UserRole": "caseworker-caa",
    "CRUD": "CRU"
  },
  {
    "LiveFrom": "01/10/2020",
    "CaseTypeID": "FinancialRemedyMVP2",
    "CaseFieldID": "appRespondentRep",
    "UserRole": "caseworker-caa",
    "CRUD": "CRU"
  },
  {
    "LiveFrom": "01/10/2020",
    "CaseTypeID": "FinancialRemedyMVP2",
    "CaseFieldID": "rSolicitorName",
    "UserRole": "caseworker-caa",
    "CRUD": "CRU"
  },
  {
    "LiveFrom": "01/10/2020",
    "CaseTypeID": "FinancialRemedyMVP2",
    "CaseFieldID": "rSolicitorFirm",
    "UserRole": "caseworker-caa",
    "CRUD": "CRU"
  },
  {
    "LiveFrom": "01/10/2020",
    "CaseTypeID": "FinancialRemedyMVP2",
    "CaseFieldID": "rSolicitorReference",
    "UserRole": "caseworker-caa",
    "CRUD": "CRU"
  },
  {
    "LiveFrom": "01/10/2020",
    "CaseTypeID": "FinancialRemedyMVP2",
    "CaseFieldID": "rSolicitorAddress",
    "UserRole": "caseworker-caa",
    "CRUD": "CRU"
  },
  {
    "LiveFrom": "01/10/2020",
    "CaseTypeID": "FinancialRemedyMVP2",
    "CaseFieldID": "rSolicitorPhone",
    "UserRole": "caseworker-caa",
    "CRUD": "CRU"
  },
  {
    "LiveFrom": "01/10/2020",
    "CaseTypeID": "FinancialRemedyMVP2",
    "CaseFieldID": "rSolicitorEmail",
    "UserRole": "caseworker-caa",
    "CRUD": "CRU"
  },
  {
    "LiveFrom": "01/10/2020",
    "CaseTypeID": "FinancialRemedyMVP2",
    "CaseFieldID": "rSolicitorDXnumber",
    "UserRole": "caseworker-caa",
    "CRUD": "CRU"
  },
  {
    "LiveFrom": "01/10/2020",
    "CaseTypeID": "FinancialRemedyMVP2",
    "CaseFieldID": "respondentAddress",
    "UserRole": "caseworker-caa",
    "CRUD": "CRU"
  },
  {
    "LiveFrom": "01/10/2020",
    "CaseTypeID": "FinancialRemedyMVP2",
    "CaseFieldID": "respondentPhone",
    "UserRole": "caseworker-caa",
    "CRUD": "CRU"
  },
  {
    "LiveFrom": "01/10/2020",
    "CaseTypeID": "FinancialRemedyMVP2",
    "CaseFieldID": "respondentEmail",
    "UserRole": "caseworker-caa",
    "CRUD": "CRU"
  },
  {
    "LiveFrom": "01/10/2020",
    "CaseTypeID": "FinancialRemedyMVP2",
    "CaseFieldID": "natureOfApplication2",
    "UserRole": "caseworker-caa",
    "CRUD": "CRU"
  },
  {
    "LiveFrom": "01/10/2020",
    "CaseTypeID": "FinancialRemedyMVP2",
    "CaseFieldID": "natureOfApplication3a",
    "UserRole": "caseworker-caa",
    "CRUD": "CRU"
  },
  {
    "LiveFrom": "01/10/2020",
    "CaseTypeID": "FinancialRemedyMVP2",
    "CaseFieldID": "natureOfApplication3b",
    "UserRole": "caseworker-caa",
    "CRUD": "CRU"
  },
  {
    "LiveFrom": "01/10/2020",
    "CaseTypeID": "FinancialRemedyMVP2",
    "CaseFieldID": "orderForChildrenQuestion1",
    "UserRole": "caseworker-caa",
    "CRUD": "CRU"
  },
  {
    "LiveFrom": "01/10/2020",
    "CaseTypeID": "FinancialRemedyMVP2",
    "CaseFieldID": "natureOfApplication5",
    "UserRole": "caseworker-caa",
    "CRUD": "CRU"
  },
  {
    "LiveFrom": "01/10/2020",
    "CaseTypeID": "FinancialRemedyMVP2",
    "CaseFieldID": "natureOfApplication6",
    "UserRole": "caseworker-caa",
    "CRUD": "CRU"
  },
  {
    "LiveFrom": "01/10/2020",
    "CaseTypeID": "FinancialRemedyMVP2",
    "CaseFieldID": "natureOfApplication7",
    "UserRole": "caseworker-caa",
    "CRUD": "CRU"
  },
  {
    "LiveFrom": "01/10/2020",
    "CaseTypeID": "FinancialRemedyMVP2",
    "CaseFieldID": "consentOrder",
    "UserRole": "caseworker-caa",
    "CRUD": "CRU"
  },
  {
    "LiveFrom": "01/10/2020",
    "CaseTypeID": "FinancialRemedyMVP2",
    "CaseFieldID": "d81Question",
    "UserRole": "caseworker-caa",
    "CRUD": "CRU"
  },
  {
    "LiveFrom": "01/10/2020",
    "CaseTypeID": "FinancialRemedyMVP2",
    "CaseFieldID": "d81Joint",
    "UserRole": "caseworker-caa",
    "CRUD": "CRU"
  },
  {
    "LiveFrom": "01/10/2020",
    "CaseTypeID": "FinancialRemedyMVP2",
    "CaseFieldID": "d81Applicant",
    "UserRole": "caseworker-caa",
    "CRUD": "CRU"
  },
  {
    "LiveFrom": "01/10/2020",
    "CaseTypeID": "FinancialRemedyMVP2",
    "CaseFieldID": "d81Respondent",
    "UserRole": "caseworker-caa",
    "CRUD": "CRU"
  },
  {
    "LiveFrom": "01/10/2020",
    "CaseTypeID": "FinancialRemedyMVP2",
    "CaseFieldID": "pensionCollection",
    "UserRole": "caseworker-caa",
    "CRUD": "CRU"
  },
  {
    "LiveFrom": "01/10/2020",
    "CaseTypeID": "FinancialRemedyMVP2",
    "CaseFieldID": "otherCollection",
    "UserRole": "caseworker-caa",
    "CRUD": "CRU"
  },
  {
    "LiveFrom": "01/10/2020",
    "CaseTypeID": "FinancialRemedyMVP2",
    "CaseFieldID": "divRoleOfFrApplicant",
    "UserRole": "caseworker-caa",
    "CRUD": "CRU"
  },
  {
    "LiveFrom": "01/10/2020",
    "CaseTypeID": "FinancialRemedyMVP2",
    "CaseFieldID": "applicantAddressConfidential",
    "UserRole": "caseworker-caa",
    "CRUD": "CRU"
  },
  {
    "LiveFrom": "01/10/2020",
    "CaseTypeID": "FinancialRemedyMVP2",
    "CaseFieldID": "respondentAddressConfidential",
    "UserRole": "caseworker-caa",
    "CRUD": "CRU"
  }
]