[
  {
    "LiveFrom": "01/01/2017",
    "CaseTypeID": "FinancialRemedyContested",
    "ID": "intv4FdrCaseDocuments",
    "Label": "FDR Case documents",
    "FieldType": "Collection",
    "FieldTypeParameter": "FR_uploadCaseDocument",
    "SecurityClassification": "Public"
  },
  {
    "LiveFrom": "01/01/2017",
    "CaseTypeID": "FinancialRemedyContested",
    "ID": "intv4HearingBundles",
    "Label": "Hearing Bundles",
    "FieldType": "Collection",
    "FieldTypeParameter": "FR_uploadCaseDocument",
    "SecurityClassification": "Public"
  },
  {
    "LiveFrom": "01/01/2017",
    "CaseTypeID": "FinancialRemedyContested",
    "ID": "intv4FormEsExhibits",
    "Label": "Forms E & Exhibits",
    "FieldType": "Collection",
    "FieldTypeParameter": "FR_uploadCaseDocument",
    "SecurityClassification": "Public"
  },
  {
    "LiveFrom": "01/01/2017",
    "CaseTypeID": "FinancialRemedyContested",
    "ID": "intv4Chronologies",
    "Label": "Chronologies and Statements of Issues",
    "FieldType": "Collection",
    "FieldTypeParameter": "FR_uploadCaseDocument",
    "SecurityClassification": "Public"
  },
  {
    "LiveFrom": "01/01/2017",
    "CaseTypeID": "FinancialRemedyContested",
    "ID": "intv4Qa",
    "Label": "Questionnaires & Answers to Questionnaires & Exhibits",
    "FieldType": "Collection",
    "FieldTypeParameter": "FR_uploadCaseDocument",
    "SecurityClassification": "Public"
  },
  {
    "LiveFrom": "01/01/2017",
    "CaseTypeID": "FinancialRemedyContested",
    "ID": "intv4StmtsExhibits",
    "Label": "Statements & Exhibits",
    "FieldType": "Collection",
    "FieldTypeParameter": "FR_uploadCaseDocument",
    "SecurityClassification": "Public"
  },
  {
    "LiveFrom": "01/01/2017",
    "CaseTypeID": "FinancialRemedyContested",
    "ID": "intv4Summaries",
    "Label": "Case Summaries",
    "FieldType": "Collection",
    "FieldTypeParameter": "FR_uploadCaseDocument",
    "SecurityClassification": "Public"
  },
  {
    "LiveFrom": "01/01/2017",
    "CaseTypeID": "FinancialRemedyContested",
    "ID": "intv4FormHs",
    "Label": "Forms H",
    "FieldType": "Collection",
    "FieldTypeParameter": "FR_uploadCaseDocument",
    "SecurityClassification": "Public"
  },
  {
    "LiveFrom": "01/01/2017",
    "CaseTypeID": "FinancialRemedyContested",
    "ID": "intv4ExpertEvidence",
    "Label": "Expert Evidence",
    "FieldType": "Collection",
    "FieldTypeParameter": "FR_uploadCaseDocument",
    "SecurityClassification": "Public"
  },
  {
    "LiveFrom": "01/01/2017",
    "CaseTypeID": "FinancialRemedyContested",
    "ID": "intv4CorrespDocs",
    "Label": "Correspondence",
    "FieldType": "Collection",
    "FieldTypeParameter": "FR_uploadCaseDocument",
    "SecurityClassification": "Public"
  },
  {
    "LiveFrom": "01/01/2017",
    "CaseTypeID": "FinancialRemedyContested",
    "ID": "intv4Other",
    "Label": "Other",
    "FieldType": "Collection",
    "FieldTypeParameter": "FR_uploadCaseDocument",
    "SecurityClassification": "Public"
  },
  {
    "LiveFrom": "01/01/2017",
    "CaseTypeID": "FinancialRemedyContested",
    "ID": "intv3FdrCaseDocuments",
    "Label": "FDR Case documents",
    "FieldType": "Collection",
    "FieldTypeParameter": "FR_uploadCaseDocument",
    "SecurityClassification": "Public"
  },
  {
    "LiveFrom": "01/01/2017",
    "CaseTypeID": "FinancialRemedyContested",
    "ID": "intv3HearingBundles",
    "Label": "Hearing Bundles",
    "FieldType": "Collection",
    "FieldTypeParameter": "FR_uploadCaseDocument",
    "SecurityClassification": "Public"
  },
  {
    "LiveFrom": "01/01/2017",
    "CaseTypeID": "FinancialRemedyContested",
    "ID": "intv3FormEsExhibits",
    "Label": "Forms E & Exhibits",
    "FieldType": "Collection",
    "FieldTypeParameter": "FR_uploadCaseDocument",
    "SecurityClassification": "Public"
  },
  {
    "LiveFrom": "01/01/2017",
    "CaseTypeID": "FinancialRemedyContested",
    "ID": "intv3Chronologies",
    "Label": "Chronologies and Statements of Issues",
    "FieldType": "Collection",
    "FieldTypeParameter": "FR_uploadCaseDocument",
    "SecurityClassification": "Public"
  },
  {
    "LiveFrom": "01/01/2017",
    "CaseTypeID": "FinancialRemedyContested",
    "ID": "intv3Qa",
    "Label": "Questionnaires & Answers to Questionnaires & Exhibits",
    "FieldType": "Collection",
    "FieldTypeParameter": "FR_uploadCaseDocument",
    "SecurityClassification": "Public"
  },
  {
    "LiveFrom": "01/01/2017",
    "CaseTypeID": "FinancialRemedyContested",
    "ID": "intv3StmtsExhibits",
    "Label": "Statements & Exhibits",
    "FieldType": "Collection",
    "FieldTypeParameter": "FR_uploadCaseDocument",
    "SecurityClassification": "Public"
  },
  {
    "LiveFrom": "01/01/2017",
    "CaseTypeID": "FinancialRemedyContested",
    "ID": "intv3Summaries",
    "Label": "Case Summaries",
    "FieldType": "Collection",
    "FieldTypeParameter": "FR_uploadCaseDocument",
    "SecurityClassification": "Public"
  },
  {
    "LiveFrom": "01/01/2017",
    "CaseTypeID": "FinancialRemedyContested",
    "ID": "intv3FormHs",
    "Label": "Forms H",
    "FieldType": "Collection",
    "FieldTypeParameter": "FR_uploadCaseDocument",
    "SecurityClassification": "Public"
  },
  {
    "LiveFrom": "01/01/2017",
    "CaseTypeID": "FinancialRemedyContested",
    "ID": "intv3ExpertEvidence",
    "Label": "Expert Evidence",
    "FieldType": "Collection",
    "FieldTypeParameter": "FR_uploadCaseDocument",
    "SecurityClassification": "Public"
  },
  {
    "LiveFrom": "01/01/2017",
    "CaseTypeID": "FinancialRemedyContested",
    "ID": "intv3CorrespDocs",
    "Label": "Correspondence",
    "FieldType": "Collection",
    "FieldTypeParameter": "FR_uploadCaseDocument",
    "SecurityClassification": "Public"
  },
  {
    "LiveFrom": "01/01/2017",
    "CaseTypeID": "FinancialRemedyContested",
    "ID": "intv3Other",
    "Label": "Other",
    "FieldType": "Collection",
    "FieldTypeParameter": "FR_uploadCaseDocument",
    "SecurityClassification": "Public"
  },
  {
    "LiveFrom": "01/01/2017",
    "CaseTypeID": "FinancialRemedyContested",
    "ID": "intv2FdrCaseDocuments",
    "Label": "FDR Case documents",
    "FieldType": "Collection",
    "FieldTypeParameter": "FR_uploadCaseDocument",
    "SecurityClassification": "Public"
  },
  {
    "LiveFrom": "01/01/2017",
    "CaseTypeID": "FinancialRemedyContested",
    "ID": "intv2HearingBundles",
    "Label": "Hearing Bundles",
    "FieldType": "Collection",
    "FieldTypeParameter": "FR_uploadCaseDocument",
    "SecurityClassification": "Public"
  },
  {
    "LiveFrom": "01/01/2017",
    "CaseTypeID": "FinancialRemedyContested",
    "ID": "intv2FormEsExhibits",
    "Label": "Forms E & Exhibits",
    "FieldType": "Collection",
    "FieldTypeParameter": "FR_uploadCaseDocument",
    "SecurityClassification": "Public"
  },
  {
    "LiveFrom": "01/01/2017",
    "CaseTypeID": "FinancialRemedyContested",
    "ID": "intv2Chronologies",
    "Label": "Chronologies and Statements of Issues",
    "FieldType": "Collection",
    "FieldTypeParameter": "FR_uploadCaseDocument",
    "SecurityClassification": "Public"
  },
  {
    "LiveFrom": "01/01/2017",
    "CaseTypeID": "FinancialRemedyContested",
    "ID": "intv2Qa",
    "Label": "Questionnaires & Answers to Questionnaires & Exhibits",
    "FieldType": "Collection",
    "FieldTypeParameter": "FR_uploadCaseDocument",
    "SecurityClassification": "Public"
  },
  {
    "LiveFrom": "01/01/2017",
    "CaseTypeID": "FinancialRemedyContested",
    "ID": "intv2StmtsExhibits",
    "Label": "Statements & Exhibits",
    "FieldType": "Collection",
    "FieldTypeParameter": "FR_uploadCaseDocument",
    "SecurityClassification": "Public"
  },
  {
    "LiveFrom": "01/01/2017",
    "CaseTypeID": "FinancialRemedyContested",
    "ID": "intv2Summaries",
    "Label": "Case Summaries",
    "FieldType": "Collection",
    "FieldTypeParameter": "FR_uploadCaseDocument",
    "SecurityClassification": "Public"
  },
  {
    "LiveFrom": "01/01/2017",
    "CaseTypeID": "FinancialRemedyContested",
    "ID": "intv2FormHs",
    "Label": "Forms H",
    "FieldType": "Collection",
    "FieldTypeParameter": "FR_uploadCaseDocument",
    "SecurityClassification": "Public"
  },
  {
    "LiveFrom": "01/01/2017",
    "CaseTypeID": "FinancialRemedyContested",
    "ID": "intv2ExpertEvidence",
    "Label": "Expert Evidence",
    "FieldType": "Collection",
    "FieldTypeParameter": "FR_uploadCaseDocument",
    "SecurityClassification": "Public"
  },
  {
    "LiveFrom": "01/01/2017",
    "CaseTypeID": "FinancialRemedyContested",
    "ID": "intv2CorrespDocs",
    "Label": "Correspondence",
    "FieldType": "Collection",
    "FieldTypeParameter": "FR_uploadCaseDocument",
    "SecurityClassification": "Public"
  },
  {
    "LiveFrom": "01/01/2017",
    "CaseTypeID": "FinancialRemedyContested",
    "ID": "intv2Other",
    "Label": "Other",
    "FieldType": "Collection",
    "FieldTypeParameter": "FR_uploadCaseDocument",
    "SecurityClassification": "Public"
  },
  {
    "LiveFrom": "01/01/2017",
    "CaseTypeID": "FinancialRemedyContested",
    "ID": "intv1FdrCaseDocuments",
    "Label": "FDR Case documents",
    "FieldType": "Collection",
    "FieldTypeParameter": "FR_uploadCaseDocument",
    "SecurityClassification": "Public"
  },
  {
    "LiveFrom": "01/01/2017",
    "CaseTypeID": "FinancialRemedyContested",
    "ID": "intv1HearingBundles",
    "Label": "Hearing Bundles",
    "FieldType": "Collection",
    "FieldTypeParameter": "FR_uploadCaseDocument",
    "SecurityClassification": "Public"
  },
  {
    "LiveFrom": "01/01/2017",
    "CaseTypeID": "FinancialRemedyContested",
    "ID": "intv1FormEsExhibits",
    "Label": "Forms E & Exhibits",
    "FieldType": "Collection",
    "FieldTypeParameter": "FR_uploadCaseDocument",
    "SecurityClassification": "Public"
  },
  {
    "LiveFrom": "01/01/2017",
    "CaseTypeID": "FinancialRemedyContested",
    "ID": "intv1Chronologies",
    "Label": "Chronologies and Statements of Issues",
    "FieldType": "Collection",
    "FieldTypeParameter": "FR_uploadCaseDocument",
    "SecurityClassification": "Public"
  },
  {
    "LiveFrom": "01/01/2017",
    "CaseTypeID": "FinancialRemedyContested",
    "ID": "intv1Qa",
    "Label": "Questionnaires & Answers to Questionnaires & Exhibits",
    "FieldType": "Collection",
    "FieldTypeParameter": "FR_uploadCaseDocument",
    "SecurityClassification": "Public"
  },
  {
    "LiveFrom": "01/01/2017",
    "CaseTypeID": "FinancialRemedyContested",
    "ID": "intv1StmtsExhibits",
    "Label": "Statements & Exhibits",
    "FieldType": "Collection",
    "FieldTypeParameter": "FR_uploadCaseDocument",
    "SecurityClassification": "Public"
  },
  {
    "LiveFrom": "01/01/2017",
    "CaseTypeID": "FinancialRemedyContested",
    "ID": "intv1Summaries",
    "Label": "Case Summaries",
    "FieldType": "Collection",
    "FieldTypeParameter": "FR_uploadCaseDocument",
    "SecurityClassification": "Public"
  },
  {
    "LiveFrom": "01/01/2017",
    "CaseTypeID": "FinancialRemedyContested",
    "ID": "intv1FormHs",
    "Label": "Forms H",
    "FieldType": "Collection",
    "FieldTypeParameter": "FR_uploadCaseDocument",
    "SecurityClassification": "Public"
  },
  {
    "LiveFrom": "01/01/2017",
    "CaseTypeID": "FinancialRemedyContested",
    "ID": "intv1ExpertEvidence",
    "Label": "Expert Evidence",
    "FieldType": "Collection",
    "FieldTypeParameter": "FR_uploadCaseDocument",
    "SecurityClassification": "Public"
  },
  {
    "LiveFrom": "01/01/2017",
    "CaseTypeID": "FinancialRemedyContested",
    "ID": "intv1CorrespDocs",
    "Label": "Correspondence",
    "FieldType": "Collection",
    "FieldTypeParameter": "FR_uploadCaseDocument",
    "SecurityClassification": "Public"
  },
  {
    "LiveFrom": "01/01/2017",
    "CaseTypeID": "FinancialRemedyContested",
    "ID": "intv1Other",
    "Label": "Other",
    "FieldType": "Collection",
    "FieldTypeParameter": "FR_uploadCaseDocument",
    "SecurityClassification": "Public"
  }
]