[
  {
    "LiveFrom": "01/06/2020",
    "CaseTypeID": "FinancialRemedyContested",
    "ID": "d11",
    "Label": "D11 document",
    "FieldType": "Document",
    "SecurityClassification": "Public"
  },
  {
    "LiveFrom": "01/01/2021",
    "CaseTypeID": "FinancialRemedyContested",
    "ID": "latestDraftDirectionOrder",
    "Label": "Latest Draft Direction Order  ",
    "HintText": "PLEASE NOTE: you must upload an editable version of the draft order (for example a 'word' document) - please do not upload a PDF",
    "FieldType": "FR_ct_draftDirectionOrder",
    "SecurityClassification": "Public"
  },
  {
    "LiveFrom": "01/01/2021",
    "CaseTypeID": "FinancialRemedyContested",
    "ID": "judgesAmendedDirectionOrderCollection",
    "Label": "Judge's amended direction orders",
    "FieldType": "Collection",
    "FieldTypeParameter": "FR_ct_draftDirectionOrder",
    "SecurityClassification": "Public"
  }
]
