[
  {
    "LiveFrom": "13/12/2019",
    "CaseTypeID": "FinancialRemedyContested",
    "CaseEventID": "FR_consentOrder",
    "UserRole": "[APPSOLICITOR]",
    "CRUD": "CR"
  },
  {
    "LiveFrom": "01/01/2017",
    "CaseTypeID": "FinancialRemedyContested",
    "CaseEventID": "FR_submitUploadedCaseFiles",
    "UserRole": "[APPSOLICITOR]",
    "CRUD": "CR"
  },
  {
    "LiveFrom": "13/12/2019",
    "CaseTypeID": "FinancialRemedyContested",
    "CaseEventID": "FR_respondToConsentOrder",
    "UserRole": "[APPSOLICITOR]",
    "CRUD": "CR"
  }
]