[
  {
    "LiveFrom": "01/01/2017",
    "ID": "FR_ms_natureApplication",
    "ListElementCode": "Variation Order",
    "ListElement": "Variation Order",
    "DisplayOrder": 10
  },
  {
    "LiveFrom": "01/01/2017",
    "ID": "FR_fl_VariationOtherDocument",
    "ListElementCode": "originalOrder",
    "ListElement": "Original order",
    "DisplayOrder": 1
  },
  {
    "LiveFrom": "01/01/2017",
    "ID": "FR_fl_VariationOtherDocument",
    "ListElementCode": "Other",
    "ListElement": "Other documents",
    "DisplayOrder": 2
  }
]